defal96863/__init__.py
defal96863-3.1.5.dist-info/METADATA
defal96863-3.1.5.dist-info/WHEEL
defal96863-3.1.5.dist-info/top_level.txt
defal96863-3.1.5.dist-info/RECORD
